persona_toolkit/__init__.py
persona_toolkit/cli.py
persona_toolkit/model.py
persona_toolkit/schema_utils.py
persona_toolkit/secret_registry.py
persona_toolkit/server.py
persona_toolkit/tools_registry.py
template_project/.env
template_project/.gitignore
template_project/README.md
template_project/docker/Dockerfile
template_project/docker/run.sh
template_project/requirements.txt
template_project/secret.py
template_project/tools/echo.py
persona_toolkit-1.0.58.dist-info/METADATA
persona_toolkit-1.0.58.dist-info/WHEEL
persona_toolkit-1.0.58.dist-info/entry_points.txt
persona_toolkit-1.0.58.dist-info/RECORD
