Metadata-Version: 2.3
Name: persona-toolkit
Version: 1.0.58
Summary: Toolkit for Persona, an agent AI system — provides modular, callable tools for dynamic function execution
Author: Bruno Fortunato
Author-email: bruno.fortunato@applica.guru
Requires-Python: >=3.9
Classifier: Programming Language :: Python :: 3
Classifier: Programming Language :: Python :: 3.9
Classifier: Programming Language :: Python :: 3.10
Classifier: Programming Language :: Python :: 3.11
Classifier: Programming Language :: Python :: 3.12
Classifier: Programming Language :: Python :: 3.13
Requires-Dist: aiounittest (>=1.5.0,<2.0.0)
Requires-Dist: fastapi (>=0.115.12,<0.116.0)
Requires-Dist: pydantic (>=2.10.6,<3.0.0)
Requires-Dist: python-dotenv (>=1.0.1,<2.0.0)
Requires-Dist: rich (>=13.9.4,<14.0.0)
Requires-Dist: toml (>=0.10.2,<0.11.0)
Requires-Dist: typer (>=0.15.2,<0.16.0)
Requires-Dist: uvicorn (>=0.34.0,<0.35.0)
